optiflow/__init__.py
optiflow/functions.py
optiflow-1.1.1.dist-info/METADATA
optiflow-1.1.1.dist-info/WHEEL
optiflow-1.1.1.dist-info/top_level.txt
optiflow-1.1.1.dist-info/RECORD
