Metadata-Version: 2.1
Name: optiflow
Version: 1.1.1
Summary: Reconstruction of flows from kymographs with optimal transport
Home-page: https://github.com/sacha-ichbiah/optiflow
Author: Sacha Ichbiah
Author-email: sacha.ichbiah@college-de-france.fr
Project-URL: Team website, https://www.turlierlab.com/
Classifier: Programming Language :: Python :: 3
Classifier: License :: OSI Approved :: MIT License
Classifier: Operating System :: POSIX :: Linux
Classifier: Operating System :: MacOS
Classifier: License :: OSI Approved :: MIT License
Classifier: Intended Audience :: Science/Research
Requires-Python: <3.10,>=3.6
Requires-Dist: torch (>=1.6.0)
Requires-Dist: numpy (>=1.21.6)
Requires-Dist: polyscope (>=1.2.0)
Requires-Dist: POT (>=0.8.2)
Requires-Dist: matplotlib (>=3.3.1)
